ph_toolbox/__init__.py
ph_toolbox/base.py
ph_toolbox/config.py
ph_toolbox/constants.py
ph_toolbox/csv_store.py
ph_toolbox/event.py
ph_toolbox/notifier_ms_teams.py
ph_toolbox/retry_on_error.py
ph_toolbox/utils.py
ph_toolbox-0.1.1.dist-info/LICENSE
ph_toolbox-0.1.1.dist-info/METADATA
ph_toolbox-0.1.1.dist-info/WHEEL
ph_toolbox-0.1.1.dist-info/top_level.txt
ph_toolbox-0.1.1.dist-info/RECORD
